imio.pm.wsclient-2.0.6-py3.13-nspkg.pth
imio/pm/wsclient/__init__.py
imio/pm/wsclient/config.py
imio/pm/wsclient/configure.zcml
imio/pm/wsclient/events.py
imio/pm/wsclient/interfaces.py
imio/pm/wsclient/setuphandlers.py
imio/pm/wsclient/subscribers.zcml
imio/pm/wsclient/testing-settings.zcml
imio/pm/wsclient/testing.py
imio/pm/wsclient/testing.zcml
imio/pm/wsclient/upgrade.py
imio/pm/wsclient/browser/__init__.py
imio/pm/wsclient/browser/annexes.py
imio/pm/wsclient/browser/configure.zcml
imio/pm/wsclient/browser/forms.py
imio/pm/wsclient/browser/redirect.py
imio/pm/wsclient/browser/settings.py
imio/pm/wsclient/browser/viewlets.py
imio/pm/wsclient/browser/views.py
imio/pm/wsclient/browser/vocabularies.py
imio/pm/wsclient/browser/images/annex.png
imio/pm/wsclient/browser/images/doc.png
imio/pm/wsclient/browser/images/docx.png
imio/pm/wsclient/browser/images/odt.png
imio/pm/wsclient/browser/images/pdf.png
imio/pm/wsclient/browser/images/rtf.png
imio/pm/wsclient/browser/images/send_to_plonemeeting.png
imio/pm/wsclient/browser/javascripts/popups.js
imio/pm/wsclient/browser/templates/contentprovider-widget.pt
imio/pm/wsclient/browser/templates/display_data_to_send.pt
imio/pm/wsclient/browser/templates/plonemeeting_infos.pt
imio/pm/wsclient/browser/templates/show_errors_in_overlay_form.pt
imio/pm/wsclient/locales/PloneMeeting.pot
imio/pm/wsclient/locales/imio.pm.wsclient.pot
imio/pm/wsclient/locales/sync_pos.sh
imio/pm/wsclient/locales/en/LC_MESSAGES/PloneMeeting.po
imio/pm/wsclient/locales/en/LC_MESSAGES/imio.pm.wsclient.po
imio/pm/wsclient/locales/fr/LC_MESSAGES/PloneMeeting.po
imio/pm/wsclient/locales/fr/LC_MESSAGES/imio.pm.wsclient.po
imio/pm/wsclient/profiles/default/browserlayer.xml
imio/pm/wsclient/profiles/default/controlpanel.xml
imio/pm/wsclient/profiles/default/imio_pm_wsclient_marker.txt
imio/pm/wsclient/profiles/default/import_steps.xml
imio/pm/wsclient/profiles/default/jsregistry.xml
imio/pm/wsclient/profiles/default/metadata.xml
imio_pm_wsclient-2.0.6.dist-info/METADATA
imio_pm_wsclient-2.0.6.dist-info/WHEEL
imio_pm_wsclient-2.0.6.dist-info/namespace_packages.txt
imio_pm_wsclient-2.0.6.dist-info/top_level.txt
imio_pm_wsclient-2.0.6.dist-info/RECORD
