Metadata-Version: 2.4
Name: imio.pm.wsclient
Version: 2.0.6
Summary: WebServices Client for PloneMeeting
Home-page: https://github.com/IMIO/imio.pm.wsclient
Author: Gauthier Bastien
Author-email: devs@imio.be
License: GPL
Classifier: License :: OSI Approved :: GNU General Public License (GPL)
Classifier: Framework :: Plone
Classifier: Framework :: Plone :: 4.3
Classifier: Programming Language :: Python
Classifier: Programming Language :: Python :: 2.7
Requires-Dist: setuptools
Requires-Dist: collective.z3cform.datagridfield
Requires-Dist: imio.pm.locales
Requires-Dist: plone.memoize
Requires-Dist: requests
Requires-Dist: six
Provides-Extra: test
Requires-Dist: plone.app.testing; extra == "test"
Requires-Dist: plonemeeting.restapi; extra == "test"
Requires-Dist: mock; extra == "test"
Dynamic: author
Dynamic: author-email
Dynamic: classifier
Dynamic: description
Dynamic: home-page
Dynamic: keywords
Dynamic: license
Dynamic: provides-extra
Dynamic: requires-dist
Dynamic: summary
